{
  "updated": "2026-04-30T00:12:14.746011Z",
  "fg_us": {
    "value": 77,
    "label": "Extreme Greed"
  },
  "fg_crypto": {
    "value": 29,
    "label": "Fear"
  },
  "bitcoin": {
    "price": 75725,
    "change_pct": -0.79
  },
  "ethereum": {
    "price": 2252.97,
    "change_pct": -1.58
  },
  "qqq": {
    "price": 661.57,
    "sma200": 601.7,
    "rsi": 70.7,
    "change_pct": 0.61
  },
  "spy": {
    "price": 711.58,
    "change_pct": -0.02
  },
  "vix": {
    "value": 18.81
  },
  "ndx": {
    "price": 27186.98,
    "change_pct": 0.58
  },
  "gold": {
    "price": 4572.5,
    "change_pct": -0.41
  },
  "oil": {
    "price": 107.25,
    "change_pct": 7.33
  },
  "usdkrw": {
    "price": 1484.48,
    "change_pct": 0.85
  },
  "jpykrw": {
    "price": 925.4,
    "change_pct": 0.31
  },
  "fg_kr": {
    "value": 71,
    "label": "Greed"
  },
  "put_call": {
    "value": 1.33
  }
}