{
  "updated": "2026-04-15T09:47:28.663058Z",
  "fg_us": {
    "value": 71,
    "label": "Greed"
  },
  "fg_crypto": {
    "value": 23,
    "label": "Extreme Fear"
  },
  "bitcoin": {
    "price": 73978,
    "change_pct": -0.68
  },
  "ethereum": {
    "price": 2321.29,
    "change_pct": -2.74
  },
  "qqq": {
    "price": 628.6,
    "sma200": 596.13,
    "rsi": 67.97,
    "change_pct": 1.82
  },
  "spy": {
    "price": 694.46,
    "change_pct": 1.22
  },
  "vix": {
    "value": 18.29
  },
  "ndx": {
    "price": 25842.0,
    "change_pct": 1.81
  },
  "gold": {
    "price": 4821.7,
    "change_pct": -0.07
  },
  "oil": {
    "price": 92.53,
    "change_pct": 1.37
  },
  "usdkrw": {
    "price": 1478.08,
    "change_pct": 0.08
  },
  "jpykrw": {
    "price": 930.59,
    "change_pct": 0.32
  },
  "fg_kr": {
    "value": 62,
    "label": "Greed"
  },
  "put_call": {
    "value": 1.118
  }
}